common/__init__.py
common/common.py
arkade_etl_functions-1.1.2.dist-info/LICENSE.txt
arkade_etl_functions-1.1.2.dist-info/METADATA
arkade_etl_functions-1.1.2.dist-info/WHEEL
arkade_etl_functions-1.1.2.dist-info/top_level.txt
arkade_etl_functions-1.1.2.dist-info/RECORD
