Metadata-Version: 2.1
Name: arkade-etl-functions
Version: 1.1.2
Summary: Common library package for etl-functions
Home-page: https://github.com/arkade-digital/etl-functions
Author: Tim Moon
Author-email: timmoon.arkade@gmail.com
License: UNKNOWN
Platform: UNKNOWN
Classifier: Programming Language :: Python :: 3
Classifier: License :: OSI Approved :: MIT License
Classifier: Operating System :: OS Independent
Requires-Python: >=3.6
